shopyo_settings/__init__.py
shopyo_settings/helpers.py
shopyo_settings/info.json
shopyo_settings/models.py
shopyo_settings/upload.py
shopyo_settings/view.py
shopyo_settings-1.3.0.dist-info/METADATA
shopyo_settings-1.3.0.dist-info/WHEEL
shopyo_settings-1.3.0.dist-info/top_level.txt
shopyo_settings-1.3.0.dist-info/RECORD
