Metadata-Version: 2.4
Name: shopyo_settings
Version: 1.3.0
Summary: Module for managing settings in shopyo
Author-email: Abdur-Rahmaan Janhangeer <arj.python@gmail.com>
Project-URL: Homepage, https://github.com/shopyo/shopyo
Project-URL: Bug Tracker, https://github.com/shopyo/shopyo/issues
Keywords: shopyo
Classifier: Programming Language :: Python :: 3
Classifier: License :: OSI Approved :: BSD License
Classifier: Operating System :: OS Independent
Requires-Python: >=3.8
Requires-Dist: shopyo
